kalmus/__init__.py
kalmus/command_line_generator.py
kalmus/command_line_gui.py
kalmus/barcodes/Barcode.py
kalmus/barcodes/BarcodeGenerator.py
kalmus/barcodes/__init__.py
kalmus/data/kalmus_icon.ico
kalmus/data/kalmus_icon.jpg
kalmus/data/kalmus_icon.xbm
kalmus/data/mission_impossible_Bright_Whole_frame_Color.json
kalmus/tkinter_windows/GenerateBarcodeWindow.py
kalmus/tkinter_windows/LoadJsonWindow.py
kalmus/tkinter_windows/LoadStackWindow.py
kalmus/tkinter_windows/MainWindowVersion2.py
kalmus/tkinter_windows/ReshapeBarcodeWindow.py
kalmus/tkinter_windows/SaveBarcodeWindow.py
kalmus/tkinter_windows/SaveImageWindow.py
kalmus/tkinter_windows/StatsInfoWindow.py
kalmus/tkinter_windows/__init__.py
kalmus/tkinter_windows/gui_utils.py
kalmus/tkinter_windows/meta_info_windows/MetaInfoWindow.py
kalmus/tkinter_windows/meta_info_windows/SpecifyMetaDataWindow.py
kalmus/tkinter_windows/meta_info_windows/WhichBarcodeCheckMeta.py
kalmus/tkinter_windows/meta_info_windows/__init__.py
kalmus/tkinter_windows/plot_barcodes_windows/PlotBarcodeWindow.py
kalmus/tkinter_windows/plot_barcodes_windows/WhichBarcodeInspectWindow.py
kalmus/tkinter_windows/plot_barcodes_windows/__init__.py
kalmus/tkinter_windows/time_points_windows/CalibrateBarcodeTimeWindow.py
kalmus/tkinter_windows/time_points_windows/CheckTimePointWindow.py
kalmus/tkinter_windows/time_points_windows/DisplaySavedFramesWindow.py
kalmus/tkinter_windows/time_points_windows/__init__.py
kalmus/utils/__init__.py
kalmus/utils/artist.py
kalmus/utils/measure_utils.py
kalmus/utils/visualization_utils.py
kalmus-1.3.14.dist-info/LICENSE
kalmus-1.3.14.dist-info/METADATA
kalmus-1.3.14.dist-info/WHEEL
kalmus-1.3.14.dist-info/entry_points.txt
kalmus-1.3.14.dist-info/top_level.txt
kalmus-1.3.14.dist-info/RECORD
