Metadata-Version: 2.1
Name: kalmus
Version: 1.3.14
Summary: kalmus film color analysis tool
Home-page: https://github.com/KALMUS-Color-Toolkit/KALMUS
Author: Yida Chen, Eric Faden, Nathan Ryan
Author-email: yc015@bucknell.edu
License: MIT
Keywords: film,color analysis,data visualization
Platform: UNKNOWN
Classifier: License :: OSI Approved :: MIT License
Classifier: Programming Language :: Python :: 3
Classifier: Programming Language :: Python :: 3.7
Classifier: Programming Language :: Python :: 3.8
Classifier: Development Status :: 5 - Production/Stable
Classifier: Intended Audience :: Education
Classifier: Intended Audience :: Science/Research
Classifier: Operating System :: OS Independent
Classifier: Topic :: Multimedia :: Video
Classifier: Topic :: Software Development :: Libraries :: Python Modules
Classifier: Topic :: Software Development :: User Interfaces
Requires-Python: >=3.7
Requires-Dist: numpy
Requires-Dist: opencv-python
Requires-Dist: scikit-image (>=0.16.2)
Requires-Dist: matplotlib (>=3.2.2)
Requires-Dist: scikit-learn
Requires-Dist: biopython
Requires-Dist: scipy
Requires-Dist: kiwisolver (>=1.3.1)
Requires-Dist: pandas
